MANIFEST.in
MIT-LICENSE.txt
README.rst
RELEASE-VERSION
TODO.mkd
setup.py
concurrent_tree_crawler/__init__.py
concurrent_tree_crawler/abstract_cmdln_navigators_creator.py
concurrent_tree_crawler/abstract_node.py
concurrent_tree_crawler/abstract_tree_accessor.py
concurrent_tree_crawler/abstract_tree_navigator.py
concurrent_tree_crawler/cmdln_multithreaded_crawler.py
concurrent_tree_crawler/crawler_thread.py
concurrent_tree_crawler/crawlers_manager.py
concurrent_tree_crawler/multithreaded_crawler.py
concurrent_tree_crawler/navigator_tree_wrapper.py
concurrent_tree_crawler/rw_lock_tree_accessor.py
concurrent_tree_crawler/simple_dfs_crawler.py
concurrent_tree_crawler/standard_node.py
concurrent_tree_crawler/tree_accessor.py
concurrent_tree_crawler/tree_saver_thread.py
concurrent_tree_crawler/xml_tree_serialization.py
concurrent_tree_crawler.egg-info/PKG-INFO
concurrent_tree_crawler.egg-info/SOURCES.txt
concurrent_tree_crawler.egg-info/dependency_links.txt
concurrent_tree_crawler.egg-info/requires.txt
concurrent_tree_crawler.egg-info/top_level.txt
concurrent_tree_crawler/bin/run_clean_sample_download_crawler.sh
concurrent_tree_crawler/bin/run_sample_download_crawler.py
concurrent_tree_crawler/bin/sample_download_crawler.py
concurrent_tree_crawler/common/__init__.py
concurrent_tree_crawler/common/activity_schedule.py
concurrent_tree_crawler/common/delayed_http_files_server.py
concurrent_tree_crawler/common/dir_tree_comparer.py
concurrent_tree_crawler/common/file_helper.py
concurrent_tree_crawler/common/logger.py
concurrent_tree_crawler/common/resources.py
concurrent_tree_crawler/common/tempdir.py
concurrent_tree_crawler/common/version.py
concurrent_tree_crawler/common/test/__init__.py
concurrent_tree_crawler/common/test/activity_schedule_test.py
concurrent_tree_crawler/common/test/dir_tree_comparer_test.py
concurrent_tree_crawler/common/test/data/dir_tree_comparer/additional_dir/01/bash_script.sh
concurrent_tree_crawler/common/test/data/dir_tree_comparer/additional_dir/01/sub_01/sub_01-01/01_01-file.txt
concurrent_tree_crawler/common/test/data/dir_tree_comparer/additional_dir/01/sub_01/sub_01-01/Other file.text
