Metadata-Version: 1.0
Name: concurrent-tree-crawler
Version: 0.8.8
Summary: A generic concurrent tree crawling algorithm with a sample implementation for website crawling.
Home-page: http://github.com/mkobos/tree_crawler
Author: Mateusz Kobos
Author-email: mateusz@mkobos.com
License: MIT-LICENSE.txt
Keywords: concurrent,tree,website,crawler
Platform: UNKNOWN
Classifier: Development Status :: 3 - Alpha
Classifier: Environment :: Console
Classifier: Intended Audience :: Developers
Classifier: Programming Language :: Python
Classifier: Programming Language :: Python :: 2.7
Classifier: License :: OSI Approved :: MIT License
Classifier: Topic :: Internet :: WWW/HTTP
Classifier: Operating System :: OS Independent
